{
  "days": [
    {
      "leg": "Fly to Santa Barbara",
      "nm": 0,
      "hrs": 0,
      "overnight": "",
      "tags": [
        "layover"
      ],
      "fuelStop": false,
      "tideWarning": false,
      "highlights": [],
      "note": "",
      "day": 1
    },
    {
      "leg": "Move-in Day",
      "nm": 0,
      "hrs": 0,
      "overnight": "",
      "tags": [
        "layover"
      ],
      "fuelStop": false,
      "tideWarning": false,
      "highlights": [],
      "note": "",
      "day": 2
    },
    {
      "leg": "Fly to Seattle",
      "nm": 0,
      "hrs": 0,
      "overnight": "",
      "tags": [
        "layover"
      ],
      "fuelStop": false,
      "tideWarning": false,
      "highlights": [],
      "note": "",
      "day": 3
    }
  ],
  "places": {
    "1": [
      {
        "id": "e4dde30d-626f-4968-8000-d50a9bc5bc2b",
        "name": "Rosewood Miramar Beach",
        "address": "",
        "phone": "",
        "website": "",
        "placeId": "",
        "category": "accommodation",
        "notes": "Ultra-luxury beachfront resort with private beach access, spa, and fine dining. Located west of downtown with stunning coastal views.",
        "addedAt": "2026-05-03T20:36:07.599Z",
        "mapsProvider": null
      },
      {
        "id": "3c7cb364-d820-4f74-b86b-a8f36e73ed68",
        "name": "Four Seasons Resort The Biltmore Santa Barbara",
        "address": "",
        "phone": "",
        "website": "",
        "placeId": "",
        "category": "accommodation",
        "notes": "Historic oceanfront luxury property with lush gardens, multiple pools, and Michelin-starred dining options in Montecito.",
        "addedAt": "2026-05-03T20:36:07.599Z",
        "mapsProvider": null
      },
      {
        "id": "58f2533e-0d35-423b-9c36-26d517a5e2c0",
        "name": "Santa Barbara Hillside House",
        "address": "",
        "phone": "",
        "website": "",
        "placeId": "",
        "category": "accommodation",
        "notes": "Intimate luxury inn with contemporary design, ocean views, and personalized service near State Street shopping and dining.",
        "addedAt": "2026-05-03T20:36:07.599Z",
        "mapsProvider": null
      },
      {
        "id": "1a66231c-246a-4d59-8cb2-26e0a67d95b8",
        "name": "Belmond El Encanto",
        "address": "",
        "phone": "",
        "website": "",
        "placeId": "",
        "category": "accommodation",
        "notes": "Elegant hillside retreat with gardens, spa, and fine dining overlooking the city and Pacific Ocean.",
        "addedAt": "2026-05-03T20:36:07.599Z",
        "mapsProvider": null
      }
    ]
  },
  "directions": {},
  "routes": {},
  "flights": {},
  "rentalCars": {
    "3": [
      {
        "id": "4cd684f7-1bdb-46bc-963c-f09f850a8d66",
        "agency": "Hertz",
        "confirmation": "aslkdjfakl;jsdfklajsd;flkjs",
        "pickupLocation": "",
        "dropoffLocation": "",
        "notes": "",
        "addedAt": "2026-05-03T01:08:50.229Z"
      }
    ]
  },
  "highlights": {
    "1": [
      "Get rental car",
      "Check into hotel",
      "Shopping for dorm room?",
      "Dinner",
      "Book a spa treatment at sunset to recover from travel",
      "Dinner reservations at The Biltmore or Rosewood restaurants for arrival night",
      "Request ocean-view rooms for morning views before departure to Hudson River"
    ],
    "2": [
      "Drive to campus",
      "Check-in",
      "Unload car",
      "Move-in and set up room"
    ],
    "3": [
      "Check out of hotel",
      "Return rental car",
      "Go to airport"
    ]
  },
  "notes": {
    "1": "TODO: Get SEA -> SBA airfare (round trip for 2, one-way for Hudson!)\nTODO: Reserve rental car (big SUV)\nTodo: Get hotel\n"
  },
  "startDate": "2026-09-18",
  "title": "Take Hudson to College",
  "subtitle": "Move into UCSB",
  "itineraryNotes": ""
}